odoo8_addon_account_default_draft_move-8.0.1.0.0.99.dev22-py2.7-nspkg.pth
odoo8_addon_account_default_draft_move-8.0.1.0.0.99.dev22.dist-info/METADATA
odoo8_addon_account_default_draft_move-8.0.1.0.0.99.dev22.dist-info/RECORD
odoo8_addon_account_default_draft_move-8.0.1.0.0.99.dev22.dist-info/WHEEL
odoo8_addon_account_default_draft_move-8.0.1.0.0.99.dev22.dist-info/namespace_packages.txt
odoo8_addon_account_default_draft_move-8.0.1.0.0.99.dev22.dist-info/top_level.txt
odoo_addons/account_default_draft_move/README.rst
odoo_addons/account_default_draft_move/__init__.py
odoo_addons/account_default_draft_move/__openerp__.py
odoo_addons/account_default_draft_move/account.py
odoo_addons/account_default_draft_move/account_bank_statement.py
odoo_addons/account_default_draft_move/account_view.xml
odoo_addons/account_default_draft_move/invoice_view.xml
odoo_addons/account_default_draft_move/res_config.py
odoo_addons/account_default_draft_move/res_config_view.xml
odoo_addons/account_default_draft_move/i18n/account_default_draft_move.pot
odoo_addons/account_default_draft_move/i18n/am.po
odoo_addons/account_default_draft_move/i18n/ar.po
odoo_addons/account_default_draft_move/i18n/bg.po
odoo_addons/account_default_draft_move/i18n/bs.po
odoo_addons/account_default_draft_move/i18n/ca.po
odoo_addons/account_default_draft_move/i18n/ca_ES.po
odoo_addons/account_default_draft_move/i18n/cs.po
odoo_addons/account_default_draft_move/i18n/da.po
odoo_addons/account_default_draft_move/i18n/de.po
odoo_addons/account_default_draft_move/i18n/el_GR.po
odoo_addons/account_default_draft_move/i18n/en_GB.po
odoo_addons/account_default_draft_move/i18n/es.po
odoo_addons/account_default_draft_move/i18n/es_CR.po
odoo_addons/account_default_draft_move/i18n/es_EC.po
odoo_addons/account_default_draft_move/i18n/es_ES.po
odoo_addons/account_default_draft_move/i18n/es_MX.po
odoo_addons/account_default_draft_move/i18n/es_PE.po
odoo_addons/account_default_draft_move/i18n/es_VE.po
odoo_addons/account_default_draft_move/i18n/et.po
odoo_addons/account_default_draft_move/i18n/fi.po
odoo_addons/account_default_draft_move/i18n/fr.po
odoo_addons/account_default_draft_move/i18n/fr_CA.po
odoo_addons/account_default_draft_move/i18n/fr_CH.po
odoo_addons/account_default_draft_move/i18n/gl.po
odoo_addons/account_default_draft_move/i18n/hr.po
