Metadata-Version: 2.1
Name: odoo8-addon-account-default-draft-move
Version: 8.0.1.0.0.99.dev22
Summary: Move in draft state by default
Home-page: http://www.camptocamp.com
Author: Camptocamp,ACSONE SA/NV,Odoo Community Association (OCA)
Author-email: support@odoo-community.org
License: AGPL-3
Platform: UNKNOWN
Classifier: Programming Language :: Python
Classifier: Framework :: Odoo
Classifier: License :: OSI Approved :: GNU Affero General Public License v3
Requires-Python: ~=2.7
Requires-Dist: odoo8-addon-account-constraints
Requires-Dist: odoo (<9.0a,>=8.0a)
